django_reactive_framework/__init__.py
django_reactive_framework/apps.py
django_reactive_framework/urls.py
django_reactive_framework/core/__init__.py
django_reactive_framework/core/base.py
django_reactive_framework/core/public.py
django_reactive_framework/core/reactive_binary_operators.py
django_reactive_framework/core/reactive_function.py
django_reactive_framework/core/reactive_unary_operators.py
django_reactive_framework/core/utils.py
django_reactive_framework/core/expressions/__init__.py
django_reactive_framework/core/expressions/implementations.py
django_reactive_framework/core/expressions/interfaces.py
django_reactive_framework/resources/reactscripts.js
django_reactive_framework/templates/reactive_example.html
django_reactive_framework/templates/reactive_example_base.html
django_reactive_framework/templatetags/__init__.py
django_reactive_framework/templatetags/reactive.py
django_reactive_framework-0.0.1.dist-info/LICENSE
django_reactive_framework-0.0.1.dist-info/METADATA
django_reactive_framework-0.0.1.dist-info/WHEEL
django_reactive_framework-0.0.1.dist-info/top_level.txt
django_reactive_framework-0.0.1.dist-info/zip-safe
django_reactive_framework-0.0.1.dist-info/RECORD
