Metadata-Version: 2.1
Name: django-reactive-framework
Version: 0.0.1
Summary: A minimalistic reactive framework for Django Templates
Home-page: https://github.com/Tal500/django-reactive-framework
Author: Tal Hadad
License: MIT
Project-URL: Bug Tracker, https://github.com/Tal500/django-reactive-framework/issues
Keywords: django,reactive,javascript,html,frontend,reactive-programming
Classifier: Development Status :: 1 - Planning
Classifier: License :: OSI Approved :: MIT License
Classifier: Programming Language :: Python :: 3
Classifier: Intended Audience :: Developers
Classifier: Operating System :: OS Independent
Classifier: Environment :: Web Environment
Classifier: Framework :: Django
Requires-Python: >=3.8
License-File: LICENSE
Requires-Dist: Django (>=3.1)
